novexity/__init__.py
novexity/search.py
novexity/user_agents.py
novexity/aiohttp_ip_rotator/__init__.py
novexity/aiohttp_ip_rotator/rotator.py
novexity/requests_ip_rotator/__init__.py
novexity/requests_ip_rotator/ip_rotator.py
Novexity-1.0.6.dist-info/LICENSE
Novexity-1.0.6.dist-info/METADATA
Novexity-1.0.6.dist-info/WHEEL
Novexity-1.0.6.dist-info/top_level.txt
Novexity-1.0.6.dist-info/RECORD
