Metadata-Version: 2.1
Name: Novexity
Version: 1.0.6
Summary: Freely Scrape Google Search Results Fast and Easy ✨
Home-page: https://github.com/NorkzYT/Novexity
Author: NorkzYT
License-File: LICENSE
Requires-Dist: beautifulsoup4
Requires-Dist: requests
Requires-Dist: boto3
Requires-Dist: aiobotocore
Requires-Dist: aioboto3
Requires-Dist: python-dotenv
